pioner/__init__.py
pioner/runUI.py
pioner/assets/__init__.py
pioner/back/__init__.py
pioner/back/ai_device.py
pioner/back/ao_data_generators.py
pioner/back/ao_device.py
pioner/back/daq_device.py
pioner/back/debug.py
pioner/back/experiment_manager.py
pioner/back/fastheat.py
pioner/back/iso_mode.py
pioner/back/nanocontrol_tango.py
pioner/front/SetProg_widget.py
pioner/front/__init__.py
pioner/front/calibWindow.py
pioner/front/configWindow.py
pioner/front/mainWindow.py
pioner/front/mainWindowUi.py
pioner/front/messageWindows.py
pioner/front/procFastHeatWidget.py
pioner/front/resultsDataWidget.py
pioner/front/virtualDevice.py
pioner/settings/__init__.py
pioner/settings/default_calibration.json
pioner/settings/default_settings.json
pioner/shared/__init__.py
pioner/shared/calibration.py
pioner/shared/constants.py
pioner/shared/settings.py
pioner/shared/utils.py
ppioner-0.0.7.dist-info/LICENSE
ppioner-0.0.7.dist-info/METADATA
ppioner-0.0.7.dist-info/WHEEL
ppioner-0.0.7.dist-info/entry_points.txt
ppioner-0.0.7.dist-info/top_level.txt
ppioner-0.0.7.dist-info/RECORD
