Metadata-Version: 2.1
Name: ppioner
Version: 0.0.7
Summary: Basic software to operate PIONER device (former Nanocal)
Author-email: awesome author <awesome@author.edu>
License: MIT
Keywords: nanocalorimetry,DAQ
Classifier: Programming Language :: Python :: 3
Classifier: License :: OSI Approved :: MIT License
Classifier: Operating System :: OS Independent
Requires-Python: >=3.8
License-File: LICENSE
Requires-Dist: matplotlib (==3.5.2)
Requires-Dist: numpy (==1.22.4)
Requires-Dist: pandas (==1.4.2)
Requires-Dist: scipy (==1.8.1)
Requires-Dist: h5py (==3.7.0)
Requires-Dist: pytango (==9.3.3)
Requires-Dist: requests (==2.31.0)
Requires-Dist: sortedcontainers (==2.4.0)
Requires-Dist: importlib-metadata ; python_version < "3.8"
Provides-Extra: gui
Requires-Dist: silx (==1.0.0) ; extra == 'gui'
Requires-Dist: pyqt5 (==5.15.6) ; extra == 'gui'
Provides-Extra: server
Requires-Dist: uldaq (==1.2.3) ; extra == 'server'
